pulumi_provider_fivetran/__init__.py
pulumi_provider_fivetran/_inputs.py
pulumi_provider_fivetran/_utilities.py
pulumi_provider_fivetran/connector.py
pulumi_provider_fivetran/connector_certificates.py
pulumi_provider_fivetran/connector_fingerprints.py
pulumi_provider_fivetran/connector_schedule.py
pulumi_provider_fivetran/connector_schema_config.py
pulumi_provider_fivetran/dbt_git_project_config.py
pulumi_provider_fivetran/dbt_project.py
pulumi_provider_fivetran/dbt_transformation.py
pulumi_provider_fivetran/destination.py
pulumi_provider_fivetran/destination_certificates.py
pulumi_provider_fivetran/destination_fingerprints.py
pulumi_provider_fivetran/external_logging.py
pulumi_provider_fivetran/get_connection.py
pulumi_provider_fivetran/get_connection_certificates.py
pulumi_provider_fivetran/get_connection_fingerprints.py
pulumi_provider_fivetran/get_connections.py
pulumi_provider_fivetran/get_connector.py
pulumi_provider_fivetran/get_connector_certificates.py
pulumi_provider_fivetran/get_connector_fingerprints.py
pulumi_provider_fivetran/get_connectors.py
pulumi_provider_fivetran/get_connectors_metadata.py
pulumi_provider_fivetran/get_dbt_models.py
pulumi_provider_fivetran/get_dbt_project.py
pulumi_provider_fivetran/get_dbt_projects.py
pulumi_provider_fivetran/get_dbt_transformation.py
pulumi_provider_fivetran/get_destination.py
pulumi_provider_fivetran/get_destination_certificates.py
pulumi_provider_fivetran/get_destination_fingerprints.py
pulumi_provider_fivetran/get_destinations.py
pulumi_provider_fivetran/get_external_logging.py
pulumi_provider_fivetran/get_external_logs.py
pulumi_provider_fivetran/get_group.py
pulumi_provider_fivetran/get_group_connections.py
pulumi_provider_fivetran/get_group_connectors.py
pulumi_provider_fivetran/get_group_service_account.py
pulumi_provider_fivetran/get_group_ssh_key.py
pulumi_provider_fivetran/get_group_users.py
pulumi_provider_fivetran/get_groups.py
pulumi_provider_fivetran/get_hybrid_deployment_agent.py
pulumi_provider_fivetran-0.0.0.dist-info/METADATA
pulumi_provider_fivetran-0.0.0.dist-info/WHEEL
pulumi_provider_fivetran-0.0.0.dist-info/top_level.txt
pulumi_provider_fivetran-0.0.0.dist-info/RECORD
